calculatorfirstversion/__init__.py
calculatorfirstversion-0.0.1.dist-info/LICENCE.txt
calculatorfirstversion-0.0.1.dist-info/METADATA
calculatorfirstversion-0.0.1.dist-info/WHEEL
calculatorfirstversion-0.0.1.dist-info/top_level.txt
calculatorfirstversion-0.0.1.dist-info/RECORD
