Metadata-Version: 2.1
Name: calculatorfirstversion
Version: 0.0.1
Summary: This is a very basic calculator
Home-page: UNKNOWN
Author: Fatemeh Honarvar
Author-email: el.honarvar@gmail.com
License: UNKNOWN
Platform: UNKNOWN
Classifier: Programming Language :: Python :: 3
Classifier: License :: OSI Approved :: MIT License
Classifier: Operating System :: OS Independent
License-File: LICENCE.txt
